aldegonde/__init__.py
aldegonde/auto.py
aldegonde/c3301.py
aldegonde/column.py
aldegonde/disk.py
aldegonde/masc.py
aldegonde/pasc.py
aldegonde/pgsc.py
aldegonde/trns.py
aldegonde/analysis/__init__.py
aldegonde/analysis/autokey.py
aldegonde/analysis/c3301twist.py
aldegonde/analysis/friedman.py
aldegonde/analysis/modchecker.py
aldegonde/analysis/split.py
aldegonde/analysis/table.py
aldegonde/analysis/twist.py
aldegonde/build/setup.py
aldegonde/data/__init__.py
aldegonde/data/ngrams/__init__.py
aldegonde/data/ngrams/english/__init__.py
aldegonde/data/ngrams/runeglish/__init__.py
aldegonde/fitness/ioc.py
aldegonde/grams/__init__.py
aldegonde/grams/bigram_diagram.py
aldegonde/grams/color.py
aldegonde/maths/__init__.py
aldegonde/maths/factor.py
aldegonde/maths/modular.py
aldegonde/maths/moebius.py
aldegonde/maths/primes.py
aldegonde/maths/totient.py
aldegonde/stats/__init__.py
aldegonde/stats/compare.py
aldegonde/stats/dist.py
aldegonde/stats/entropy.py
aldegonde/stats/hamming.py
aldegonde/stats/ioc.py
aldegonde/stats/isomorph.py
aldegonde/stats/kappa.py
aldegonde/stats/ngrams.py
aldegonde/stats/repeats.py
aldegonde-0.0.3.dist-info/LICENSE
aldegonde-0.0.3.dist-info/METADATA
aldegonde-0.0.3.dist-info/WHEEL
aldegonde-0.0.3.dist-info/top_level.txt
aldegonde-0.0.3.dist-info/RECORD
