Metadata-Version: 2.1
Name: aldegonde
Version: 0.0.3
Summary: Classical Cryptography Library
Author-email: Michel Oosterhof <michel@oosterhof.net>
License: ISC License
Project-URL: homepage, https://github.com/micheloosterhof/aldegonde
Project-URL: documentation, https://readthedocs.org
Project-URL: repository, https://github.com/micheloosterhof/aldegonde
Project-URL: changelog, https://github.com/me/spam/blob/master/CHANGELOG.md
Keywords: cryptanalysis,cryptology,cryptography
Classifier: Development Status :: 3 - Alpha
Classifier: Programming Language :: Python
Classifier: License :: OSI Approved :: ISC License (ISCL)
Classifier: Operating System :: OS Independent
Classifier: Topic :: Security :: Cryptography
Classifier: Topic :: Software Development :: Libraries :: Python Modules
Requires-Python: >=3.9
License-File: LICENSE
